LICENSE
MANIFEST.in
README.rst
setup.cfg
setup.py
geofound/__about__.py
geofound/__init__.py
geofound/capacity.py
geofound/checking_tools.py
geofound/exceptions.py
geofound/fadums_chart.py
geofound/models.py
geofound/output.py
geofound/settlement.py
geofound/tables_of_dyn_coefficients.py
geofound.egg-info/PKG-INFO
geofound.egg-info/SOURCES.txt
geofound.egg-info/dependency_links.txt
geofound.egg-info/not-zip-safe
geofound.egg-info/requires.txt
geofound.egg-info/top_level.txt
geofound/damping/__init__.py
geofound/damping/gazetas_1991.py
geofound/damping/pais_1988.py
geofound/stiffness/__init__.py
geofound/stiffness/gazetas_1991.py
geofound/stiffness/general.py
geofound/stiffness/pais_1988.py