Metadata-Version: 2.1
Name: geofound
Version: 1.1.3
Summary: A package to assess the bearing capacity and settlement of geofound
Home-page: https://github.com/eng-tools/geofound
Author: Maxim Millen
Author-email: mmi46@uclive.ac.nz
License: MIT
Keywords: geotechnical engineering foundations settlement
Platform: UNKNOWN
Classifier: Development Status :: 5 - Production/Stable
Classifier: Intended Audience :: Science/Research
Classifier: Topic :: Scientific/Engineering
Classifier: License :: OSI Approved :: MIT License
Classifier: Programming Language :: Python :: 3
Requires-Python: >=3
Provides-Extra: test
License-File: LICENSE
